arca/__init__.py
arca/client.py
arca/exceptions.py
arca/models.py
arca/version.py
arca_ai_vault-0.2.2.dist-info/licenses/LICENSE
tests/__init__.py
tests/test_error_handling.py
arca_ai_vault-0.2.2.dist-info/METADATA
arca_ai_vault-0.2.2.dist-info/WHEEL
arca_ai_vault-0.2.2.dist-info/top_level.txt
arca_ai_vault-0.2.2.dist-info/RECORD
