Metadata-Version: 2.4
Name: arca-ai-vault
Version: 0.2.2
Summary: Python SDK for Arca - Private data vault for personal AI assistants
Home-page: https://github.com/xbora/arca-python-sdk
Author: Arca Team
Author-email: Arca Team <support@arca.build>
License: MIT
Project-URL: Homepage, https://arca.build
Project-URL: Documentation, https://docs.arca.build
Project-URL: Repository, https://github.com/xbora/arca-python-sdk
Keywords: arca,ai,data,vault,storage,vectors,embeddings
Classifier: Development Status :: 4 - Beta
Classifier: Intended Audience :: Developers
Classifier: License :: OSI Approved :: MIT License
Classifier: Programming Language :: Python :: 3
Classifier: Programming Language :: Python :: 3.8
Classifier: Programming Language :: Python :: 3.9
Classifier: Programming Language :: Python :: 3.10
Classifier: Programming Language :: Python :: 3.11
Classifier: Programming Language :: Python :: 3.12
Requires-Python: >=3.8
License-File: LICENSE
Requires-Dist: requests>=2.31.0
Provides-Extra: dev
Requires-Dist: pytest>=7.4.0; extra == "dev"
Requires-Dist: pytest-cov>=4.1.0; extra == "dev"
Requires-Dist: black>=23.7.0; extra == "dev"
Requires-Dist: flake8>=6.1.0; extra == "dev"
Requires-Dist: mypy>=1.5.0; extra == "dev"
Dynamic: author
Dynamic: home-page
Dynamic: license-file
Dynamic: requires-python
